devtools_base64/__init__.py
devtools_base64-1.0.0.dist-info/METADATA
devtools_base64-1.0.0.dist-info/WHEEL
devtools_base64-1.0.0.dist-info/top_level.txt
devtools_base64-1.0.0.dist-info/RECORD
