Metadata-Version: 2.1
Name: devtools-base64
Version: 1.0.0
Summary: Base64 encoder/decoder with UTF-8 support
Home-page: https://devtools.at/tools/base64
Author: DevTools.at
Author-email: hello@devtools.at
Project-URL: Homepage, https://devtools.at/tools/base64
Project-URL: Repository, https://github.com/nicokant/base64
Classifier: Development Status :: 4 - Beta
Classifier: Intended Audience :: Developers
Classifier: License :: OSI Approved :: MIT License
Classifier: Programming Language :: Python :: 3
Requires-Python: >=3.8
